function/function.py
kimleo03_homework-0.0.4.dist-info/LICENSE
kimleo03_homework-0.0.4.dist-info/METADATA
kimleo03_homework-0.0.4.dist-info/WHEEL
kimleo03_homework-0.0.4.dist-info/top_level.txt
kimleo03_homework-0.0.4.dist-info/RECORD
